betiq/__init__.py
betiq/caller.py
betiq/event_odds.py
betiq/historical_odds.py
betiq/odds.py
betiq/scores.py
betiq/sports.py
betiq-18.dist-info/LICENSE
betiq-18.dist-info/METADATA
betiq-18.dist-info/WHEEL
betiq-18.dist-info/RECORD
